docs/__init__.py
docs/conf.py
email_service/__init__.py
email_service/email_handler.py
email_service/settings.py
email_service/version.py
email_service/sendgrid/__init__.py
email_service/sendgrid/sendgrid.py
email_service/ses/__init__.py
email_service/ses/aws_ses.py
email_service/utils/__init__.py
email_service/utils/clean_data.py
email_service/utils/constants.py
email_service/utils/functions.py
email_service/utils/validators.py
email_service-2.0.0.dist-info/LICENSE
email_service-2.0.0.dist-info/METADATA
email_service-2.0.0.dist-info/WHEEL
email_service-2.0.0.dist-info/top_level.txt
email_service-2.0.0.dist-info/RECORD
