Metadata-Version: 2.1
Name: email-service
Version: 2.0.0
Summary: Package to integrate different email services with your application in just three lines of code.
Home-page: https://github.com/ramanaditya/email-service
Author: Aditya Raman
Author-email: adityaraman96@gmail.com
License: MIT License
Project-URL: Source, https://github.com/ramanaditya/email-service
Project-URL: Tracker, https://github.com/ramanaditya/email-service/issues
Keywords: python,email,sendgrid,amazon,ses,mailgun,project,email client,setup.py
Platform: UNKNOWN
Classifier: Development Status :: 4 - Beta
Classifier: Intended Audience :: Developers
Classifier: Intended Audience :: Customer Service
Classifier: Natural Language :: English
Classifier: License :: OSI Approved :: MIT License
Classifier: Programming Language :: Python :: 3.9
Classifier: Topic :: Communications :: Email
Classifier: Topic :: Software Development :: Libraries :: Python Modules
Classifier: Operating System :: OS Independent
Requires-Python: >=3.6
License-File: LICENSE
